sonatypeliftlib/__init__.py
sonatypeliftlib/apiv1.py
sonatypeliftlib/helpers.py
sonatypeliftlib-0.0.4.dist-info/METADATA
sonatypeliftlib-0.0.4.dist-info/WHEEL
sonatypeliftlib-0.0.4.dist-info/top_level.txt
sonatypeliftlib-0.0.4.dist-info/RECORD
