Metadata-Version: 2.1
Name: sonatypeliftlib
Version: 0.0.4
Summary: Helper methods to allow easier interfacing to the V1 Api of Sonatype Lift
Home-page: https://github.com/doddi/sonatypeliftlib
Author: Mark Dodgson
Author-email: mark.dodgson@googlemail.com
License: MIT
Project-URL: Homepage, https://github.com/doddi/sonatypeliftlib
Keywords: sonatype lift
Platform: UNKNOWN
Classifier: Programming Language :: Python :: 3
Classifier: License :: OSI Approved :: MIT License
Classifier: Operating System :: OS Independent
Requires-Python: >=3.6
